reldoc/__init__.py
reldoc/main.py
reldoc-1.3.1.dist-info/METADATA
reldoc-1.3.1.dist-info/WHEEL
reldoc-1.3.1.dist-info/entry_points.txt
reldoc-1.3.1.dist-info/top_level.txt
reldoc-1.3.1.dist-info/RECORD
